threelaws/__init__.py
threelaws/first_law.py
threelaws/second_law.py
threelaws/third_law.py
threelaws/zeroeth_law.py
threelaws-1.0.0.dist-info/LICENSE
threelaws-1.0.0.dist-info/METADATA
threelaws-1.0.0.dist-info/WHEEL
threelaws-1.0.0.dist-info/top_level.txt
threelaws-1.0.0.dist-info/RECORD
